rad_dino/__init__.py
rad_dino/utils.py
rad_dino-0.1.1.dist-info/WHEEL
rad_dino-0.1.1.dist-info/METADATA
rad_dino-0.1.1.dist-info/RECORD
