Metadata-Version: 2.3
Name: rad-dino
Version: 0.1.1
Summary: Vision encoder for chest X-rays.
Author: Microsoft Health Futures
Author-email: Microsoft Health Futures <innereyedev@microsoft.com>
Requires-Dist: einops
Requires-Dist: jaxtyping
Requires-Dist: pillow
Requires-Dist: requests
Requires-Dist: safetensors
Requires-Dist: transformers[torch]
Requires-Dist: typer
Requires-Python: >=3.10
Project-URL: Documentation, https://huggingface.co/microsoft/rad-dino/blob/main/README.md
Project-URL: Homepage, https://huggingface.co/microsoft/rad-dino
Project-URL: Issue tracker, https://huggingface.co/microsoft/rad-dino/discussions/new
Project-URL: Source, https://huggingface.co/microsoft/rad-dino
